[
  {
    "team": {
      "id": "CIN",
      "city": "Cincinnati",
      "nick": "Reds",
      "full": "Cincinnati Reds",
      "div": {
        "id": "national-league-central",
        "name": "National League Central"
      },
      "conf": {
        "id": "national-league",
        "name": "National League"
      }
    },
    "stats": {
      "gp": 21,
      "w": 13,
      "l": 8,
      "gb_div": "-",
      "gb_wc": "-",
      "pct": ".619",
      "stk": "W2",
      "rf": 71,
      "ra": 82,
      "rd": -11
    },
    "rnk": {
      "lg": "5",
      "cf": "5",
      "dv": "1",
      "clinch": ""
    }
  },
  {
    "team": {
      "id": "STL",
      "city": "St. Louis",
      "nick": "Cardinals",
      "full": "St. Louis Cardinals",
      "div": {
        "id": "national-league-central",
        "name": "National League Central"
      },
      "conf": {
        "id": "national-league",
        "name": "National League"
      }
    },
    "stats": {
      "gp": 20,
      "w": 12,
      "l": 8,
      "gb_div": "0.5",
      "gb_wc": "-",
      "pct": ".600",
      "stk": "W4",
      "rf": 96,
      "ra": 106,
      "rd": -10
    },
    "rnk": {
      "lg": "7",
      "cf": "7",
      "dv": "2",
      "clinch": ""
    }
  },
  {
    "team": {
      "id": "MIL",
      "city": "Milwaukee",
      "nick": "Brewers",
      "full": "Milwaukee Brewers",
      "div": {
        "id": "national-league-central",
        "name": "National League Central"
      },
      "conf": {
        "id": "national-league",
        "name": "National League"
      }
    },
    "stats": {
      "gp": 20,
      "w": 12,
      "l": 8,
      "gb_div": "0.5",
      "gb_wc": "-",
      "pct": ".600",
      "stk": "W4",
      "rf": 103,
      "ra": 82,
      "rd": 21
    },
    "rnk": {
      "lg": "6",
      "cf": "6",
      "dv": "3",
      "clinch": ""
    }
  },
  {
    "team": {
      "id": "PIT",
      "city": "Pittsburgh",
      "nick": "Pirates",
      "full": "Pittsburgh Pirates",
      "div": {
        "id": "national-league-central",
        "name": "National League Central"
      },
      "conf": {
        "id": "national-league",
        "name": "National League"
      }
    },
    "stats": {
      "gp": 21,
      "w": 12,
      "l": 9,
      "gb_div": "1.0",
      "gb_wc": "0.5",
      "pct": ".571",
      "stk": "L1",
      "rf": 107,
      "ra": 85,
      "rd": 22
    },
    "rnk": {
      "lg": "8",
      "cf": "8",
      "dv": "4",
      "clinch": ""
    }
  },
  {
    "team": {
      "id": "CHC",
      "city": "Chicago",
      "nick": "Cubs",
      "full": "Chicago Cubs",
      "div": {
        "id": "national-league-central",
        "name": "National League Central"
      },
      "conf": {
        "id": "national-league",
        "name": "National League"
      }
    },
    "stats": {
      "gp": 20,
      "w": 11,
      "l": 9,
      "gb_div": "1.5",
      "gb_wc": "1.0",
      "pct": ".550",
      "stk": "W4",
      "rf": 110,
      "ra": 81,
      "rd": 29
    },
    "rnk": {
      "lg": "9",
      "cf": "9",
      "dv": "5",
      "clinch": ""
    }
  }
]