[
  {
    "team": {
      "id": "CWS",
      "city": "Chicago",
      "nick": "White Sox",
      "full": "Chicago White Sox",
      "div": {
        "id": "american-league-central",
        "name": "American League Central"
      },
      "conf": {
        "id": "american-league",
        "name": "American League"
      }
    },
    "stats": {
      "gp": 71,
      "w": 38,
      "l": 33,
      "gb_div": "-",
      "gb_wc": "-",
      "pct": ".535",
      "stk": "L1",
      "rf": 335,
      "ra": 333,
      "rd": 2
    },
    "rnk": {
      "lg": "8",
      "cf": "3",
      "dv": "1",
      "clinch": ""
    }
  },
  {
    "team": {
      "id": "CLE",
      "city": "Cleveland",
      "nick": "Guardians",
      "full": "Cleveland Guardians",
      "div": {
        "id": "american-league-central",
        "name": "American League Central"
      },
      "conf": {
        "id": "american-league",
        "name": "American League"
      }
    },
    "stats": {
      "gp": 73,
      "w": 39,
      "l": 34,
      "gb_div": "-",
      "gb_wc": "+3.0",
      "pct": ".534",
      "stk": "L1",
      "rf": 290,
      "ra": 294,
      "rd": -4
    },
    "rnk": {
      "lg": "9",
      "cf": "4",
      "dv": "2",
      "clinch": ""
    }
  },
  {
    "team": {
      "id": "MIN",
      "city": "Minnesota",
      "nick": "Twins",
      "full": "Minnesota Twins",
      "div": {
        "id": "american-league-central",
        "name": "American League Central"
      },
      "conf": {
        "id": "american-league",
        "name": "American League"
      }
    },
    "stats": {
      "gp": 75,
      "w": 35,
      "l": 40,
      "gb_div": "5.0",
      "gb_wc": "2.0",
      "pct": ".467",
      "stk": "W3",
      "rf": 354,
      "ra": 384,
      "rd": -30
    },
    "rnk": {
      "lg": "21",
      "cf": "9",
      "dv": "3",
      "clinch": ""
    }
  },
  {
    "team": {
      "id": "DET",
      "city": "Detroit",
      "nick": "Tigers",
      "full": "Detroit Tigers",
      "div": {
        "id": "american-league-central",
        "name": "American League Central"
      },
      "conf": {
        "id": "american-league",
        "name": "American League"
      }
    },
    "stats": {
      "gp": 73,
      "w": 30,
      "l": 43,
      "gb_div": "9.0",
      "gb_wc": "6.0",
      "pct": ".411",
      "stk": "L1",
      "rf": 299,
      "ra": 307,
      "rd": -8
    },
    "rnk": {
      "lg": "26",
      "cf": "13",
      "dv": "4",
      "clinch": ""
    }
  },
  {
    "team": {
      "id": "KC",
      "city": "Kansas City",
      "nick": "Royals",
      "full": "Kansas City Royals",
      "div": {
        "id": "american-league-central",
        "name": "American League Central"
      },
      "conf": {
        "id": "american-league",
        "name": "American League"
      }
    },
    "stats": {
      "gp": 74,
      "w": 29,
      "l": 45,
      "gb_div": "10.5",
      "gb_wc": "7.5",
      "pct": ".392",
      "stk": "L2",
      "rf": 295,
      "ra": 350,
      "rd": -55
    },
    "rnk": {
      "lg": "29",
      "cf": "15",
      "dv": "5",
      "clinch": ""
    }
  }
]