{
  "team": {
    "id": "HOU",
    "city": "Houston",
    "nick": "Astros",
    "full": "Houston Astros",
    "div": {
      "id": "american-league-west",
      "name": "American League West"
    },
    "conf": {
      "id": "american-league",
      "name": "American League"
    }
  },
  "stats": {
    "gp": 61,
    "w": 27,
    "l": 34,
    "gb_div": "4.5",
    "gb_wc": "2.5",
    "pct": ".443",
    "stk": "L1",
    "rf": 271,
    "ra": 304,
    "rd": -33
  },
  "rnk": {
    "lg": "22",
    "cf": "11",
    "dv": "4",
    "clinch": ""
  },
  "games": {
    "past": [
      {
        "game_id": "20260529-HOU-MIL-1",
        "game_time_utc": "2026-05-30 00:10:00+00:00",
        "game_date": "2026-05-29",
        "final": "Final",
        "outcome": "loss",
        "location": "Home",
        "score": [
          4,
          5
        ],
        "opponent": {
          "id": "MIL",
          "name": "Milwaukee Brewers",
          "stats": {
            "gp": 56,
            "w": 35,
            "l": 21,
            "gb_div": "-",
            "gb_wc": "-",
            "pct": ".625",
            "stk": "W1",
            "rf": 268,
            "ra": 194,
            "rd": 74
          }
        }
      },
      {
        "game_id": "20260530-HOU-MIL-1",
        "game_time_utc": "2026-05-30 20:10:00+00:00",
        "game_date": "2026-05-30",
        "final": "Final",
        "outcome": "win",
        "location": "Home",
        "score": [
          9,
          2
        ],
        "opponent": {
          "id": "MIL",
          "name": "Milwaukee Brewers",
          "stats": {
            "gp": 56,
            "w": 35,
            "l": 21,
            "gb_div": "-",
            "gb_wc": "-",
            "pct": ".625",
            "stk": "W1",
            "rf": 268,
            "ra": 194,
            "rd": 74
          }
        }
      },
      {
        "game_id": "20260531-HOU-MIL-1",
        "game_time_utc": "2026-05-31 18:10:00+00:00",
        "game_date": "2026-05-31",
        "final": "Final",
        "outcome": "loss",
        "location": "Home",
        "score": [
          0,
          2
        ],
        "opponent": {
          "id": "MIL",
          "name": "Milwaukee Brewers",
          "stats": {
            "gp": 56,
            "w": 35,
            "l": 21,
            "gb_div": "-",
            "gb_wc": "-",
            "pct": ".625",
            "stk": "W1",
            "rf": 268,
            "ra": 194,
            "rd": 74
          }
        }
      }
    ],
    "upcoming": [
      {
        "game_id": "20260602-HOU-PIT-1",
        "game_time_utc": "2026-06-03 00:10:00+00:00",
        "game_date": "2026-06-02",
        "final": "",
        "outcome": "upcoming",
        "location": "Home",
        "score": [
          null,
          null
        ],
        "opponent": {
          "id": "PIT",
          "name": "Pittsburgh Pirates",
          "stats": {
            "gp": 60,
            "w": 32,
            "l": 28,
            "gb_div": "5.0",
            "gb_wc": "-",
            "pct": ".533",
            "stk": "W3",
            "rf": 301,
            "ra": 270,
            "rd": 31
          }
        }
      },
      {
        "game_id": "20260603-HOU-PIT-1",
        "game_time_utc": "2026-06-04 00:10:00+00:00",
        "game_date": "2026-06-03",
        "final": "",
        "outcome": "upcoming",
        "location": "Home",
        "score": [
          null,
          null
        ],
        "opponent": {
          "id": "PIT",
          "name": "Pittsburgh Pirates",
          "stats": {
            "gp": 60,
            "w": 32,
            "l": 28,
            "gb_div": "5.0",
            "gb_wc": "-",
            "pct": ".533",
            "stk": "W3",
            "rf": 301,
            "ra": 270,
            "rd": 31
          }
        }
      },
      {
        "game_id": "20260604-HOU-PIT-1",
        "game_time_utc": "2026-06-05 00:10:00+00:00",
        "game_date": "2026-06-04",
        "final": "",
        "outcome": "upcoming",
        "location": "Home",
        "score": [
          null,
          null
        ],
        "opponent": {
          "id": "PIT",
          "name": "Pittsburgh Pirates",
          "stats": {
            "gp": 60,
            "w": 32,
            "l": 28,
            "gb_div": "5.0",
            "gb_wc": "-",
            "pct": ".533",
            "stk": "W3",
            "rf": 301,
            "ra": 270,
            "rd": 31
          }
        }
      },
      {
        "game_id": "20260605-HOU-ATH-1",
        "game_time_utc": "2026-06-06 00:10:00+00:00",
        "game_date": "2026-06-05",
        "final": "",
        "outcome": "upcoming",
        "location": "Home",
        "score": [
          null,
          null
        ],
        "opponent": {
          "id": "ATH",
          "name": "Athletics",
          "stats": {
            "gp": 59,
            "w": 28,
            "l": 31,
            "gb_div": "2.5",
            "gb_wc": "0.5",
            "pct": ".475",
            "stk": "L1",
            "rf": 252,
            "ra": 286,
            "rd": -34
          }
        }
      }
    ]
  },
  "standings": {
    "division": [
      {
        "team": {
          "id": "SEA",
          "city": "Seattle",
          "nick": "Mariners",
          "full": "Seattle Mariners",
          "div": {
            "id": "american-league-west",
            "name": "American League West"
          },
          "conf": {
            "id": "american-league",
            "name": "American League"
          }
        },
        "stats": {
          "gp": 60,
          "w": 31,
          "l": 29,
          "gb_div": "-",
          "gb_wc": "-",
          "pct": ".517",
          "stk": "W6",
          "rf": 255,
          "ra": 225,
          "rd": 30
        },
        "rnk": {
          "lg": "14",
          "cf": "5",
          "dv": "1",
          "clinch": ""
        }
      },
      {
        "team": {
          "id": "ATH",
          "city": "Athletics",
          "nick": "Athletics",
          "full": "Athletics",
          "div": {
            "id": "american-league-west",
            "name": "American League West"
          },
          "conf": {
            "id": "american-league",
            "name": "American League"
          }
        },
        "stats": {
          "gp": 59,
          "w": 28,
          "l": 31,
          "gb_div": "2.5",
          "gb_wc": "0.5",
          "pct": ".475",
          "stk": "L1",
          "rf": 252,
          "ra": 286,
          "rd": -34
        },
        "rnk": {
          "lg": "18",
          "cf": "7",
          "dv": "2",
          "clinch": ""
        }
      },
      {
        "team": {
          "id": "TEX",
          "city": "Texas",
          "nick": "Rangers",
          "full": "Texas Rangers",
          "div": {
            "id": "american-league-west",
            "name": "American League West"
          },
          "conf": {
            "id": "american-league",
            "name": "American League"
          }
        },
        "stats": {
          "gp": 59,
          "w": 28,
          "l": 31,
          "gb_div": "2.5",
          "gb_wc": "0.5",
          "pct": ".475",
          "stk": "W3",
          "rf": 237,
          "ra": 230,
          "rd": 7
        },
        "rnk": {
          "lg": "19",
          "cf": "8",
          "dv": "3",
          "clinch": ""
        }
      },
      {
        "team": {
          "id": "HOU",
          "city": "Houston",
          "nick": "Astros",
          "full": "Houston Astros",
          "div": {
            "id": "american-league-west",
            "name": "American League West"
          },
          "conf": {
            "id": "american-league",
            "name": "American League"
          }
        },
        "stats": {
          "gp": 61,
          "w": 27,
          "l": 34,
          "gb_div": "4.5",
          "gb_wc": "2.5",
          "pct": ".443",
          "stk": "L1",
          "rf": 271,
          "ra": 304,
          "rd": -33
        },
        "rnk": {
          "lg": "22",
          "cf": "11",
          "dv": "4",
          "clinch": ""
        }
      },
      {
        "team": {
          "id": "LAA",
          "city": "Los Angeles",
          "nick": "Angels",
          "full": "Los Angeles Angels",
          "div": {
            "id": "american-league-west",
            "name": "American League West"
          },
          "conf": {
            "id": "american-league",
            "name": "American League"
          }
        },
        "stats": {
          "gp": 60,
          "w": 23,
          "l": 37,
          "gb_div": "8.0",
          "gb_wc": "6.0",
          "pct": ".383",
          "stk": "L1",
          "rf": 255,
          "ra": 306,
          "rd": -51
        },
        "rnk": {
          "lg": "27",
          "cf": "13",
          "dv": "5",
          "clinch": ""
        }
      }
    ],
    "conference": [
      {
        "team": {
          "id": "TB",
          "city": "Tampa Bay",
          "nick": "Rays",
          "full": "Tampa Bay Rays",
          "div": {
            "id": "american-league-east",
            "name": "American League East"
          },
          "conf": {
            "id": "american-league",
            "name": "American League"
          }
        },
        "stats": {
          "gp": 56,
          "w": 36,
          "l": 20,
          "gb_div": "-",
          "gb_wc": "-",
          "pct": ".643",
          "stk": "W1",
          "rf": 262,
          "ra": 243,
          "rd": 19
        },
        "rnk": {
          "lg": "3",
          "cf": "1",
          "dv": "1",
          "clinch": ""
        }
      },
      {
        "team": {
          "id": "NYY",
          "city": "New York",
          "nick": "Yankees",
          "full": "New York Yankees",
          "div": {
            "id": "american-league-east",
            "name": "American League East"
          },
          "conf": {
            "id": "american-league",
            "name": "American League"
          }
        },
        "stats": {
          "gp": 59,
          "w": 36,
          "l": 23,
          "gb_div": "1.5",
          "gb_wc": "+7.5",
          "pct": ".610",
          "stk": "W1",
          "rf": 305,
          "ra": 207,
          "rd": 98
        },
        "rnk": {
          "lg": "5",
          "cf": "2",
          "dv": "2",
          "clinch": ""
        }
      },
      {
        "team": {
          "id": "TOR",
          "city": "Toronto",
          "nick": "Blue Jays",
          "full": "Toronto Blue Jays",
          "div": {
            "id": "american-league-east",
            "name": "American League East"
          },
          "conf": {
            "id": "american-league",
            "name": "American League"
          }
        },
        "stats": {
          "gp": 60,
          "w": 29,
          "l": 31,
          "gb_div": "9.0",
          "gb_wc": "-",
          "pct": ".483",
          "stk": "L2",
          "rf": 244,
          "ra": 251,
          "rd": -7
        },
        "rnk": {
          "lg": "17",
          "cf": "6",
          "dv": "3",
          "clinch": ""
        }
      },
      {
        "team": {
          "id": "BAL",
          "city": "Baltimore",
          "nick": "Orioles",
          "full": "Baltimore Orioles",
          "div": {
            "id": "american-league-east",
            "name": "American League East"
          },
          "conf": {
            "id": "american-league",
            "name": "American League"
          }
        },
        "stats": {
          "gp": 60,
          "w": 28,
          "l": 32,
          "gb_div": "10.0",
          "gb_wc": "1.0",
          "pct": ".467",
          "stk": "W2",
          "rf": 275,
          "ra": 313,
          "rd": -38
        },
        "rnk": {
          "lg": "20",
          "cf": "9",
          "dv": "4",
          "clinch": ""
        }
      },
      {
        "team": {
          "id": "BOS",
          "city": "Boston",
          "nick": "Red Sox",
          "full": "Boston Red Sox",
          "div": {
            "id": "american-league-east",
            "name": "American League East"
          },
          "conf": {
            "id": "american-league",
            "name": "American League"
          }
        },
        "stats": {
          "gp": 58,
          "w": 25,
          "l": 33,
          "gb_div": "12.0",
          "gb_wc": "3.0",
          "pct": ".431",
          "stk": "W2",
          "rf": 231,
          "ra": 236,
          "rd": -5
        },
        "rnk": {
          "lg": "25",
          "cf": "12",
          "dv": "5",
          "clinch": ""
        }
      },
      {
        "team": {
          "id": "CLE",
          "city": "Cleveland",
          "nick": "Guardians",
          "full": "Cleveland Guardians",
          "div": {
            "id": "american-league-central",
            "name": "American League Central"
          },
          "conf": {
            "id": "american-league",
            "name": "American League"
          }
        },
        "stats": {
          "gp": 61,
          "w": 34,
          "l": 27,
          "gb_div": "-",
          "gb_wc": "-",
          "pct": ".557",
          "stk": "L2",
          "rf": 249,
          "ra": 248,
          "rd": 1
        },
        "rnk": {
          "lg": "6",
          "cf": "3",
          "dv": "1",
          "clinch": ""
        }
      },
      {
        "team": {
          "id": "CWS",
          "city": "Chicago",
          "nick": "White Sox",
          "full": "Chicago White Sox",
          "div": {
            "id": "american-league-central",
            "name": "American League Central"
          },
          "conf": {
            "id": "american-league",
            "name": "American League"
          }
        },
        "stats": {
          "gp": 59,
          "w": 32,
          "l": 27,
          "gb_div": "1.0",
          "gb_wc": "+3.5",
          "pct": ".542",
          "stk": "W5",
          "rf": 275,
          "ra": 267,
          "rd": 8
        },
        "rnk": {
          "lg": "9",
          "cf": "4",
          "dv": "2",
          "clinch": ""
        }
      },
      {
        "team": {
          "id": "MIN",
          "city": "Minnesota",
          "nick": "Twins",
          "full": "Minnesota Twins",
          "div": {
            "id": "american-league-central",
            "name": "American League Central"
          },
          "conf": {
            "id": "american-league",
            "name": "American League"
          }
        },
        "stats": {
          "gp": 60,
          "w": 27,
          "l": 33,
          "gb_div": "6.5",
          "gb_wc": "2.0",
          "pct": ".450",
          "stk": "L5",
          "rf": 275,
          "ra": 296,
          "rd": -21
        },
        "rnk": {
          "lg": "21",
          "cf": "10",
          "dv": "3",
          "clinch": ""
        }
      },
      {
        "team": {
          "id": "KC",
          "city": "Kansas City",
          "nick": "Royals",
          "full": "Kansas City Royals",
          "div": {
            "id": "american-league-central",
            "name": "American League Central"
          },
          "conf": {
            "id": "american-league",
            "name": "American League"
          }
        },
        "stats": {
          "gp": 59,
          "w": 22,
          "l": 37,
          "gb_div": "11.0",
          "gb_wc": "6.5",
          "pct": ".373",
          "stk": "L6",
          "rf": 221,
          "ra": 280,
          "rd": -59
        },
        "rnk": {
          "lg": "28",
          "cf": "14",
          "dv": "4",
          "clinch": ""
        }
      },
      {
        "team": {
          "id": "DET",
          "city": "Detroit",
          "nick": "Tigers",
          "full": "Detroit Tigers",
          "div": {
            "id": "american-league-central",
            "name": "American League Central"
          },
          "conf": {
            "id": "american-league",
            "name": "American League"
          }
        },
        "stats": {
          "gp": 60,
          "w": 22,
          "l": 38,
          "gb_div": "11.5",
          "gb_wc": "7.0",
          "pct": ".367",
          "stk": "L4",
          "rf": 223,
          "ra": 262,
          "rd": -39
        },
        "rnk": {
          "lg": "30",
          "cf": "15",
          "dv": "5",
          "clinch": ""
        }
      },
      {
        "team": {
          "id": "SEA",
          "city": "Seattle",
          "nick": "Mariners",
          "full": "Seattle Mariners",
          "div": {
            "id": "american-league-west",
            "name": "American League West"
          },
          "conf": {
            "id": "american-league",
            "name": "American League"
          }
        },
        "stats": {
          "gp": 60,
          "w": 31,
          "l": 29,
          "gb_div": "-",
          "gb_wc": "-",
          "pct": ".517",
          "stk": "W6",
          "rf": 255,
          "ra": 225,
          "rd": 30
        },
        "rnk": {
          "lg": "14",
          "cf": "5",
          "dv": "1",
          "clinch": ""
        }
      },
      {
        "team": {
          "id": "ATH",
          "city": "Athletics",
          "nick": "Athletics",
          "full": "Athletics",
          "div": {
            "id": "american-league-west",
            "name": "American League West"
          },
          "conf": {
            "id": "american-league",
            "name": "American League"
          }
        },
        "stats": {
          "gp": 59,
          "w": 28,
          "l": 31,
          "gb_div": "2.5",
          "gb_wc": "0.5",
          "pct": ".475",
          "stk": "L1",
          "rf": 252,
          "ra": 286,
          "rd": -34
        },
        "rnk": {
          "lg": "18",
          "cf": "7",
          "dv": "2",
          "clinch": ""
        }
      },
      {
        "team": {
          "id": "TEX",
          "city": "Texas",
          "nick": "Rangers",
          "full": "Texas Rangers",
          "div": {
            "id": "american-league-west",
            "name": "American League West"
          },
          "conf": {
            "id": "american-league",
            "name": "American League"
          }
        },
        "stats": {
          "gp": 59,
          "w": 28,
          "l": 31,
          "gb_div": "2.5",
          "gb_wc": "0.5",
          "pct": ".475",
          "stk": "W3",
          "rf": 237,
          "ra": 230,
          "rd": 7
        },
        "rnk": {
          "lg": "19",
          "cf": "8",
          "dv": "3",
          "clinch": ""
        }
      },
      {
        "team": {
          "id": "HOU",
          "city": "Houston",
          "nick": "Astros",
          "full": "Houston Astros",
          "div": {
            "id": "american-league-west",
            "name": "American League West"
          },
          "conf": {
            "id": "american-league",
            "name": "American League"
          }
        },
        "stats": {
          "gp": 61,
          "w": 27,
          "l": 34,
          "gb_div": "4.5",
          "gb_wc": "2.5",
          "pct": ".443",
          "stk": "L1",
          "rf": 271,
          "ra": 304,
          "rd": -33
        },
        "rnk": {
          "lg": "22",
          "cf": "11",
          "dv": "4",
          "clinch": ""
        }
      },
      {
        "team": {
          "id": "LAA",
          "city": "Los Angeles",
          "nick": "Angels",
          "full": "Los Angeles Angels",
          "div": {
            "id": "american-league-west",
            "name": "American League West"
          },
          "conf": {
            "id": "american-league",
            "name": "American League"
          }
        },
        "stats": {
          "gp": 60,
          "w": 23,
          "l": 37,
          "gb_div": "8.0",
          "gb_wc": "6.0",
          "pct": ".383",
          "stk": "L1",
          "rf": 255,
          "ra": 306,
          "rd": -51
        },
        "rnk": {
          "lg": "27",
          "cf": "13",
          "dv": "5",
          "clinch": ""
        }
      }
    ]
  }
}