{
  "team": {
    "id": "SEA",
    "city": "Seattle",
    "nick": "Mariners",
    "full": "Seattle Mariners",
    "div": {
      "id": "american-league-west",
      "name": "American League West"
    },
    "conf": {
      "id": "american-league",
      "name": "American League"
    }
  },
  "stats": {
    "gp": 26,
    "w": 11,
    "l": 15,
    "gb_div": "2.5",
    "gb_wc": "2.5",
    "pct": ".423",
    "stk": "W1",
    "rf": 101,
    "ra": 99,
    "rd": 2
  },
  "rnk": {
    "lg": "10",
    "cf": "10",
    "dv": "4",
    "clinch": ""
  },
  "games": {
    "past": [
      {
        "game_id": "20260420-SEA-ATH-1",
        "game_time_utc": "2026-04-21 01:40:00+00:00",
        "game_date": "2026-04-20",
        "final": "Final",
        "outcome": "loss",
        "location": "Home",
        "score": [
          4,
          6
        ],
        "opponent": {
          "id": "ATH",
          "name": "Athletics",
          "stats": {
            "gp": 25,
            "w": 13,
            "l": 12,
            "gb_div": "-",
            "gb_wc": "-",
            "pct": ".520",
            "stk": "L1",
            "rf": 106,
            "ra": 121,
            "rd": -15
          }
        }
      },
      {
        "game_id": "20260421-SEA-ATH-1",
        "game_time_utc": "2026-04-22 01:40:00+00:00",
        "game_date": "2026-04-21",
        "final": "Final",
        "outcome": "loss",
        "location": "Home",
        "score": [
          2,
          5
        ],
        "opponent": {
          "id": "ATH",
          "name": "Athletics",
          "stats": {
            "gp": 25,
            "w": 13,
            "l": 12,
            "gb_div": "-",
            "gb_wc": "-",
            "pct": ".520",
            "stk": "L1",
            "rf": 106,
            "ra": 121,
            "rd": -15
          }
        }
      },
      {
        "game_id": "20260422-SEA-ATH-1",
        "game_time_utc": "2026-04-22 20:10:00+00:00",
        "game_date": "2026-04-22",
        "final": "Final",
        "outcome": "win",
        "location": "Home",
        "score": [
          5,
          4
        ],
        "opponent": {
          "id": "ATH",
          "name": "Athletics",
          "stats": {
            "gp": 25,
            "w": 13,
            "l": 12,
            "gb_div": "-",
            "gb_wc": "-",
            "pct": ".520",
            "stk": "L1",
            "rf": 106,
            "ra": 121,
            "rd": -15
          }
        }
      }
    ],
    "upcoming": [
      {
        "game_id": "20260424-STL-SEA-1",
        "game_time_utc": "2026-04-25 00:15:00+00:00",
        "game_date": "2026-04-24",
        "final": "",
        "location": "Away",
        "outcome": "upcoming",
        "score": [
          null,
          null
        ],
        "opponent": {
          "id": "STL",
          "name": "St. Louis Cardinals",
          "stats": {
            "gp": 24,
            "w": 14,
            "l": 10,
            "gb_div": "1.5",
            "gb_wc": "-",
            "pct": ".583",
            "stk": "L1",
            "rf": 112,
            "ra": 123,
            "rd": -11
          }
        }
      },
      {
        "game_id": "20260425-STL-SEA-1",
        "game_time_utc": "2026-04-25 18:15:00+00:00",
        "game_date": "2026-04-25",
        "final": "",
        "location": "Away",
        "outcome": "upcoming",
        "score": [
          null,
          null
        ],
        "opponent": {
          "id": "STL",
          "name": "St. Louis Cardinals",
          "stats": {
            "gp": 24,
            "w": 14,
            "l": 10,
            "gb_div": "1.5",
            "gb_wc": "-",
            "pct": ".583",
            "stk": "L1",
            "rf": 112,
            "ra": 123,
            "rd": -11
          }
        }
      },
      {
        "game_id": "20260426-STL-SEA-1",
        "game_time_utc": "2026-04-26 18:15:00+00:00",
        "game_date": "2026-04-26",
        "final": "",
        "location": "Away",
        "outcome": "upcoming",
        "score": [
          null,
          null
        ],
        "opponent": {
          "id": "STL",
          "name": "St. Louis Cardinals",
          "stats": {
            "gp": 24,
            "w": 14,
            "l": 10,
            "gb_div": "1.5",
            "gb_wc": "-",
            "pct": ".583",
            "stk": "L1",
            "rf": 112,
            "ra": 123,
            "rd": -11
          }
        }
      },
      {
        "game_id": "20260427-MIN-SEA-1",
        "game_time_utc": "2026-04-27 23:40:00+00:00",
        "game_date": "2026-04-27",
        "final": "",
        "location": "Away",
        "outcome": "upcoming",
        "score": [
          null,
          null
        ],
        "opponent": {
          "id": "MIN",
          "name": "Minnesota Twins",
          "stats": {
            "gp": 25,
            "w": 12,
            "l": 13,
            "gb_div": "1.5",
            "gb_wc": "1.0",
            "pct": ".480",
            "stk": "L2",
            "rf": 127,
            "ra": 116,
            "rd": 11
          }
        }
      }
    ]
  },
  "standings": {
    "division": [
      {
        "team": {
          "id": "TEX",
          "city": "Texas",
          "nick": "Rangers",
          "full": "Texas Rangers",
          "div": {
            "id": "american-league-west",
            "name": "American League West"
          },
          "conf": {
            "id": "american-league",
            "name": "American League"
          }
        },
        "stats": {
          "gp": 25,
          "w": 13,
          "l": 12,
          "gb_div": "-",
          "gb_wc": "-",
          "pct": ".520",
          "stk": "W1",
          "rf": 107,
          "ra": 92,
          "rd": 15
        },
        "rnk": {
          "lg": "6",
          "cf": "6",
          "dv": "1",
          "clinch": ""
        }
      },
      {
        "team": {
          "id": "ATH",
          "city": "Athletics",
          "nick": "Athletics",
          "full": "Athletics",
          "div": {
            "id": "american-league-west",
            "name": "American League West"
          },
          "conf": {
            "id": "american-league",
            "name": "American League"
          }
        },
        "stats": {
          "gp": 25,
          "w": 13,
          "l": 12,
          "gb_div": "-",
          "gb_wc": "-",
          "pct": ".520",
          "stk": "L1",
          "rf": 106,
          "ra": 121,
          "rd": -15
        },
        "rnk": {
          "lg": "5",
          "cf": "5",
          "dv": "2",
          "clinch": ""
        }
      },
      {
        "team": {
          "id": "LAA",
          "city": "Los Angeles",
          "nick": "Angels",
          "full": "Los Angeles Angels",
          "div": {
            "id": "american-league-west",
            "name": "American League West"
          },
          "conf": {
            "id": "american-league",
            "name": "American League"
          }
        },
        "stats": {
          "gp": 26,
          "w": 12,
          "l": 14,
          "gb_div": "1.5",
          "gb_wc": "1.5",
          "pct": ".462",
          "stk": "W1",
          "rf": 126,
          "ra": 116,
          "rd": 10
        },
        "rnk": {
          "lg": "9",
          "cf": "9",
          "dv": "3",
          "clinch": ""
        }
      },
      {
        "team": {
          "id": "SEA",
          "city": "Seattle",
          "nick": "Mariners",
          "full": "Seattle Mariners",
          "div": {
            "id": "american-league-west",
            "name": "American League West"
          },
          "conf": {
            "id": "american-league",
            "name": "American League"
          }
        },
        "stats": {
          "gp": 26,
          "w": 11,
          "l": 15,
          "gb_div": "2.5",
          "gb_wc": "2.5",
          "pct": ".423",
          "stk": "W1",
          "rf": 101,
          "ra": 99,
          "rd": 2
        },
        "rnk": {
          "lg": "10",
          "cf": "10",
          "dv": "4",
          "clinch": ""
        }
      },
      {
        "team": {
          "id": "HOU",
          "city": "Houston",
          "nick": "Astros",
          "full": "Houston Astros",
          "div": {
            "id": "american-league-west",
            "name": "American League West"
          },
          "conf": {
            "id": "american-league",
            "name": "American League"
          }
        },
        "stats": {
          "gp": 26,
          "w": 10,
          "l": 16,
          "gb_div": "3.5",
          "gb_wc": "3.5",
          "pct": ".385",
          "stk": "W1",
          "rf": 137,
          "ra": 150,
          "rd": -13
        },
        "rnk": {
          "lg": "13",
          "cf": "13",
          "dv": "5",
          "clinch": ""
        }
      }
    ],
    "conference": [
      {
        "team": {
          "id": "NYY",
          "city": "New York",
          "nick": "Yankees",
          "full": "New York Yankees",
          "div": {
            "id": "american-league-east",
            "name": "American League East"
          },
          "conf": {
            "id": "american-league",
            "name": "American League"
          }
        },
        "stats": {
          "gp": 25,
          "w": 16,
          "l": 9,
          "gb_div": "-",
          "gb_wc": "-",
          "pct": ".640",
          "stk": "W6",
          "rf": 122,
          "ra": 85,
          "rd": 37
        },
        "rnk": {
          "lg": "1",
          "cf": "1",
          "dv": "1",
          "clinch": ""
        }
      },
      {
        "team": {
          "id": "TB",
          "city": "Tampa Bay",
          "nick": "Rays",
          "full": "Tampa Bay Rays",
          "div": {
            "id": "american-league-east",
            "name": "American League East"
          },
          "conf": {
            "id": "american-league",
            "name": "American League"
          }
        },
        "stats": {
          "gp": 24,
          "w": 13,
          "l": 11,
          "gb_div": "2.5",
          "gb_wc": "+0.5",
          "pct": ".542",
          "stk": "W1",
          "rf": 116,
          "ra": 128,
          "rd": -12
        },
        "rnk": {
          "lg": "2",
          "cf": "2",
          "dv": "2",
          "clinch": ""
        }
      },
      {
        "team": {
          "id": "BAL",
          "city": "Baltimore",
          "nick": "Orioles",
          "full": "Baltimore Orioles",
          "div": {
            "id": "american-league-east",
            "name": "American League East"
          },
          "conf": {
            "id": "american-league",
            "name": "American League"
          }
        },
        "stats": {
          "gp": 25,
          "w": 12,
          "l": 13,
          "gb_div": "4.0",
          "gb_wc": "1.0",
          "pct": ".480",
          "stk": "W1",
          "rf": 111,
          "ra": 115,
          "rd": -4
        },
        "rnk": {
          "lg": "7",
          "cf": "7",
          "dv": "3",
          "clinch": ""
        }
      },
      {
        "team": {
          "id": "TOR",
          "city": "Toronto",
          "nick": "Blue Jays",
          "full": "Toronto Blue Jays",
          "div": {
            "id": "american-league-east",
            "name": "American League East"
          },
          "conf": {
            "id": "american-league",
            "name": "American League"
          }
        },
        "stats": {
          "gp": 24,
          "w": 10,
          "l": 14,
          "gb_div": "5.5",
          "gb_wc": "2.5",
          "pct": ".417",
          "stk": "L1",
          "rf": 95,
          "ra": 120,
          "rd": -25
        },
        "rnk": {
          "lg": "11",
          "cf": "11",
          "dv": "4",
          "clinch": ""
        }
      },
      {
        "team": {
          "id": "BOS",
          "city": "Boston",
          "nick": "Red Sox",
          "full": "Boston Red Sox",
          "div": {
            "id": "american-league-east",
            "name": "American League East"
          },
          "conf": {
            "id": "american-league",
            "name": "American League"
          }
        },
        "stats": {
          "gp": 25,
          "w": 9,
          "l": 16,
          "gb_div": "7.0",
          "gb_wc": "4.0",
          "pct": ".360",
          "stk": "L3",
          "rf": 92,
          "ra": 114,
          "rd": -22
        },
        "rnk": {
          "lg": "14",
          "cf": "14",
          "dv": "5",
          "clinch": ""
        }
      },
      {
        "team": {
          "id": "CLE",
          "city": "Cleveland",
          "nick": "Guardians",
          "full": "Cleveland Guardians",
          "div": {
            "id": "american-league-central",
            "name": "American League Central"
          },
          "conf": {
            "id": "american-league",
            "name": "American League"
          }
        },
        "stats": {
          "gp": 26,
          "w": 14,
          "l": 12,
          "gb_div": "-",
          "gb_wc": "-",
          "pct": ".538",
          "stk": "L1",
          "rf": 105,
          "ra": 111,
          "rd": -6
        },
        "rnk": {
          "lg": "3",
          "cf": "3",
          "dv": "1",
          "clinch": ""
        }
      },
      {
        "team": {
          "id": "DET",
          "city": "Detroit",
          "nick": "Tigers",
          "full": "Detroit Tigers",
          "div": {
            "id": "american-league-central",
            "name": "American League Central"
          },
          "conf": {
            "id": "american-league",
            "name": "American League"
          }
        },
        "stats": {
          "gp": 26,
          "w": 14,
          "l": 12,
          "gb_div": "-",
          "gb_wc": "+0.5",
          "pct": ".538",
          "stk": "W2",
          "rf": 114,
          "ra": 101,
          "rd": 13
        },
        "rnk": {
          "lg": "4",
          "cf": "4",
          "dv": "2",
          "clinch": ""
        }
      },
      {
        "team": {
          "id": "MIN",
          "city": "Minnesota",
          "nick": "Twins",
          "full": "Minnesota Twins",
          "div": {
            "id": "american-league-central",
            "name": "American League Central"
          },
          "conf": {
            "id": "american-league",
            "name": "American League"
          }
        },
        "stats": {
          "gp": 25,
          "w": 12,
          "l": 13,
          "gb_div": "1.5",
          "gb_wc": "1.0",
          "pct": ".480",
          "stk": "L2",
          "rf": 127,
          "ra": 116,
          "rd": 11
        },
        "rnk": {
          "lg": "8",
          "cf": "8",
          "dv": "3",
          "clinch": ""
        }
      },
      {
        "team": {
          "id": "CWS",
          "city": "Chicago",
          "nick": "White Sox",
          "full": "Chicago White Sox",
          "div": {
            "id": "american-league-central",
            "name": "American League Central"
          },
          "conf": {
            "id": "american-league",
            "name": "American League"
          }
        },
        "stats": {
          "gp": 25,
          "w": 10,
          "l": 15,
          "gb_div": "3.5",
          "gb_wc": "3.0",
          "pct": ".400",
          "stk": "W1",
          "rf": 104,
          "ra": 130,
          "rd": -26
        },
        "rnk": {
          "lg": "12",
          "cf": "12",
          "dv": "4",
          "clinch": ""
        }
      },
      {
        "team": {
          "id": "KC",
          "city": "Kansas City",
          "nick": "Royals",
          "full": "Kansas City Royals",
          "div": {
            "id": "american-league-central",
            "name": "American League Central"
          },
          "conf": {
            "id": "american-league",
            "name": "American League"
          }
        },
        "stats": {
          "gp": 25,
          "w": 8,
          "l": 17,
          "gb_div": "5.5",
          "gb_wc": "5.0",
          "pct": ".320",
          "stk": "L1",
          "rf": 88,
          "ra": 123,
          "rd": -35
        },
        "rnk": {
          "lg": "15",
          "cf": "15",
          "dv": "5",
          "clinch": ""
        }
      },
      {
        "team": {
          "id": "TEX",
          "city": "Texas",
          "nick": "Rangers",
          "full": "Texas Rangers",
          "div": {
            "id": "american-league-west",
            "name": "American League West"
          },
          "conf": {
            "id": "american-league",
            "name": "American League"
          }
        },
        "stats": {
          "gp": 25,
          "w": 13,
          "l": 12,
          "gb_div": "-",
          "gb_wc": "-",
          "pct": ".520",
          "stk": "W1",
          "rf": 107,
          "ra": 92,
          "rd": 15
        },
        "rnk": {
          "lg": "6",
          "cf": "6",
          "dv": "1",
          "clinch": ""
        }
      },
      {
        "team": {
          "id": "ATH",
          "city": "Athletics",
          "nick": "Athletics",
          "full": "Athletics",
          "div": {
            "id": "american-league-west",
            "name": "American League West"
          },
          "conf": {
            "id": "american-league",
            "name": "American League"
          }
        },
        "stats": {
          "gp": 25,
          "w": 13,
          "l": 12,
          "gb_div": "-",
          "gb_wc": "-",
          "pct": ".520",
          "stk": "L1",
          "rf": 106,
          "ra": 121,
          "rd": -15
        },
        "rnk": {
          "lg": "5",
          "cf": "5",
          "dv": "2",
          "clinch": ""
        }
      },
      {
        "team": {
          "id": "LAA",
          "city": "Los Angeles",
          "nick": "Angels",
          "full": "Los Angeles Angels",
          "div": {
            "id": "american-league-west",
            "name": "American League West"
          },
          "conf": {
            "id": "american-league",
            "name": "American League"
          }
        },
        "stats": {
          "gp": 26,
          "w": 12,
          "l": 14,
          "gb_div": "1.5",
          "gb_wc": "1.5",
          "pct": ".462",
          "stk": "W1",
          "rf": 126,
          "ra": 116,
          "rd": 10
        },
        "rnk": {
          "lg": "9",
          "cf": "9",
          "dv": "3",
          "clinch": ""
        }
      },
      {
        "team": {
          "id": "SEA",
          "city": "Seattle",
          "nick": "Mariners",
          "full": "Seattle Mariners",
          "div": {
            "id": "american-league-west",
            "name": "American League West"
          },
          "conf": {
            "id": "american-league",
            "name": "American League"
          }
        },
        "stats": {
          "gp": 26,
          "w": 11,
          "l": 15,
          "gb_div": "2.5",
          "gb_wc": "2.5",
          "pct": ".423",
          "stk": "W1",
          "rf": 101,
          "ra": 99,
          "rd": 2
        },
        "rnk": {
          "lg": "10",
          "cf": "10",
          "dv": "4",
          "clinch": ""
        }
      },
      {
        "team": {
          "id": "HOU",
          "city": "Houston",
          "nick": "Astros",
          "full": "Houston Astros",
          "div": {
            "id": "american-league-west",
            "name": "American League West"
          },
          "conf": {
            "id": "american-league",
            "name": "American League"
          }
        },
        "stats": {
          "gp": 26,
          "w": 10,
          "l": 16,
          "gb_div": "3.5",
          "gb_wc": "3.5",
          "pct": ".385",
          "stk": "W1",
          "rf": 137,
          "ra": 150,
          "rd": -13
        },
        "rnk": {
          "lg": "13",
          "cf": "13",
          "dv": "5",
          "clinch": ""
        }
      }
    ]
  }
}